django_tailwind_v4/__init__.py
django_tailwind_v4/apps.py
django_tailwind_v4/management/__init__.py
django_tailwind_v4/management/commands/__init__.py
django_tailwind_v4/management/commands/tailwind_build.py
django_tailwind_v4/management/commands/tailwind_init.py
django_tailwind_v4/templates/django_tailwind_v4/input.css
django_tailwind_v4/templates/django_tailwind_v4/package.json
django_tailwind_v4/templates/django_tailwind_v4/tailwind.config.js
django_tailwind_v4-0.2.3.dist-info/licenses/LICENSE
django_tailwind_v4-0.2.3.dist-info/METADATA
django_tailwind_v4-0.2.3.dist-info/WHEEL
django_tailwind_v4-0.2.3.dist-info/top_level.txt
django_tailwind_v4-0.2.3.dist-info/RECORD
