Metadata-Version: 2.4
Name: django_tailwind_v4
Version: 0.2.3
Summary: A simple Django app to integrate Tailwind CSS v4.
Author-email: kothasaikrishna <kotha.saikrishna07@gmail.com>
License: MIT License
Project-URL: Homepage, https://github.com/sai-krishna-kotha/django-tailwind4
Project-URL: Issues, https://github.com/sai-krishna-kotha/django-tailwind4/issues
Classifier: Development Status :: 4 - Beta
Classifier: Environment :: Web Environment
Classifier: Framework :: Django
Classifier: Framework :: Django :: 4.2
Classifier: Framework :: Django :: 5.0
Classifier: Intended Audience :: Developers
Classifier: License :: OSI Approved :: MIT License
Classifier: Operating System :: OS Independent
Classifier: Programming Language :: Python
Classifier: Programming Language :: Python :: 3
Classifier: Topic :: Software Development :: Build Tools
Requires-Python: >=3.8
License-File: LICENSE
Requires-Dist: Django>=4.2
Dynamic: license-file
